README.md
setup.cfg
setup.py
cartowaze/__init__.py
cartowaze.egg-info/PKG-INFO
cartowaze.egg-info/SOURCES.txt
cartowaze.egg-info/dependency_links.txt
cartowaze.egg-info/requires.txt
cartowaze.egg-info/top_level.txt
cartowaze/backends/__init__.py
cartowaze/backends/base.py
cartowaze/backends/utils.py
cartowaze/backends/waze.py
cartowaze/backends/waze_ccp_processor.py