Metadata-Version: 1.0
Name: cartowaze
Version: 0.0.2
Summary: Connect Waze data sources with CARTO
Home-page: https://github.com/CartoDB/carto-waze
Author: Jorge Sanz <jsanz@carto.com>, Daniel Carrión <daniel@carto.com>
Author-email: UNKNOWN
License: MIT
Platform: UNKNOWN
